rby1_sdk/__init__.py
rby1_sdk/_bindings/__init__.pyi
rby1_sdk/_bindings/dynamics.pyi
rby1_sdk/_bindings/math.pyi
rby1_sdk/_bindings/upc.pyi
rby1_sdk/_bindings.cpython-311-darwin.so
rby1_sdk/_robot_command.py
rby1_sdk/dynamics.py
rby1_sdk/math.py
rby1_sdk/upc.py
rby1_sdk-0.9.0.dist-info/METADATA
rby1_sdk-0.9.0.dist-info/WHEEL
rby1_sdk-0.9.0.dist-info/licenses/LICENSE
rby1_sdk-0.9.0.dist-info/licenses/NOTICE
rby1_sdk-0.9.0.dist-info/RECORD
