Metadata-Version: 2.4
Name: rby1-sdk
Version: 0.9.0
Summary: 
License: Apache-2.0
License-File: LICENSE
License-File: NOTICE
Author: Keunjun Choi
Author-email: keunjun.choi@rainbow-robotics.com
Requires-Python: >=3.10,<4.0
Classifier: License :: OSI Approved :: Apache Software License
Classifier: Programming Language :: Python :: 3
Classifier: Programming Language :: Python :: 3.10
Classifier: Programming Language :: Python :: 3.11
Classifier: Programming Language :: Python :: 3.12
Classifier: Programming Language :: Python :: 3.13
Classifier: Programming Language :: Python :: 3.14
Requires-Dist: numpy (>=2.0.1,<3.0.0)
Project-URL: Homepage, https://www.rainbow-robotics.com/
Project-URL: Repository, https://github.com/RainbowRobotics/rby1-sdk
